Metadata-Version: 2.1
Name: decpac
Version: 0.0.9
Summary: Arch Linux declarative package management
Home-page: https://gitlab.com/rendaw/decpac
Author: rendaw
License: MIT
Download-URL: https://gitlab.com/rendaw/decpac/-/archive/v0.0.9/decpac-v0.0.9.tar.gz
Platform: UNKNOWN
